HISTORY.rst
MANIFEST.in
README.md
setup.cfg
setup.py
cireqs/__init__.py
cireqs/__version__.py
cireqs/cli.py
cireqs.egg-info/PKG-INFO
cireqs.egg-info/SOURCES.txt
cireqs.egg-info/dependency_links.txt
cireqs.egg-info/entry_points.txt
cireqs.egg-info/not-zip-safe
cireqs.egg-info/requires.txt
cireqs.egg-info/top_level.txt
tests/__init__.py
tests/input_requirements_1.txt
tests/input_requirements_2.txt
tests/input_requirements_3.txt
tests/input_requirements_4.txt
tests/output_requirements_1.txt
tests/test_cli.py