Metadata-Version: 2.1
Name: cireqs
Version: 2.0.2
Summary: cli tool to verify and update requirements files
Home-page: https://github.com/trustpilot/python-cireqs
Author: jgv
Author-email: jgv@trustpilot.com
License: UNKNOWN
Keywords: cireqs requirements ci
Platform: UNKNOWN
Classifier: Development Status :: 2 - Pre-Alpha
Classifier: Intended Audience :: Developers
Classifier: Natural Language :: English
Classifier: Programming Language :: Python :: 3.4
Classifier: Programming Language :: Python :: 3.5
Classifier: Programming Language :: Python :: 3.6
Provides-Extra: test
